CONTRIBUTING.rst
LICENSE
MANIFEST.in
README.rst
setup.cfg
setup.py
tox.ini
bin/ceph-medic
ceph_medic/__init__.py
ceph_medic/check.py
ceph_medic/collector.py
ceph_medic/compat.py
ceph_medic/connection.py
ceph_medic/decorators.py
ceph_medic/generate.py
ceph_medic/loader.py
ceph_medic/log.py
ceph_medic/main.py
ceph_medic/runner.py
ceph_medic/terminal.py
ceph_medic.egg-info/PKG-INFO
ceph_medic.egg-info/SOURCES.txt
ceph_medic.egg-info/dependency_links.txt
ceph_medic.egg-info/not-zip-safe
ceph_medic.egg-info/requires.txt
ceph_medic.egg-info/top_level.txt
ceph_medic/checks/__init__.py
ceph_medic/checks/clients.py
ceph_medic/checks/cluster.py
ceph_medic/checks/common.py
ceph_medic/checks/mdss.py
ceph_medic/checks/mgrs.py
ceph_medic/checks/mons.py
ceph_medic/checks/osds.py
ceph_medic/checks/rgws.py
ceph_medic/remote/__init__.py
ceph_medic/remote/commands.py
ceph_medic/remote/functions.py
ceph_medic/remote/util.py
ceph_medic/rules/__init__.py
ceph_medic/rules/jewel.py
ceph_medic/rules/kraken.py
ceph_medic/tests/__init__.py
ceph_medic/tests/conftest.py
ceph_medic/tests/test_collector.py
ceph_medic/tests/test_log.py
ceph_medic/tests/test_main.py
ceph_medic/tests/test_runner.py
ceph_medic/tests/test_terminal.py
ceph_medic/tests/checks/__init__.py
ceph_medic/tests/checks/test_cluster.py
ceph_medic/tests/checks/test_common.py
ceph_medic/tests/checks/test_mons.py
ceph_medic/tests/checks/test_osds.py
ceph_medic/tests/remote/__init__.py
ceph_medic/tests/remote/test_commands.py
ceph_medic/tests/remote/test_functions.py
ceph_medic/tests/util/__init__.py
ceph_medic/tests/util/test_configuration.py
ceph_medic/tests/util/test_hosts.py
ceph_medic/util/__init__.py
ceph_medic/util/configuration.py
ceph_medic/util/hosts.py
ceph_medic/util/mon.py
ceph_medic/util/net.py