Metadata-Version: 1.1
Name: ceph-medic
Version: 1.0.6
Summary: detect common issues with ceph clusters
Home-page: https://github.com/ceph/ceph-medic
Author: Alfredo Deza
Author-email: contact@redhat.com
License: MIT
Keywords: ceph doctor
Platform: UNKNOWN
Classifier: Development Status :: 4 - Beta
Classifier: Intended Audience :: Developers
Classifier: License :: OSI Approved :: MIT License
Classifier: Topic :: Software Development :: Build Tools
Classifier: Topic :: Utilities
Classifier: Operating System :: MacOS :: MacOS X
Classifier: Operating System :: POSIX
Classifier: Programming Language :: Python :: 2.7
Classifier: Programming Language :: Python :: 3.4
